apertium_lint/__init__.py
apertium_lint/file_linter.py
apertium_lint/tests/__init__.py
apertium_lint/tests/base.py
apertium_lint/tests/test_cg.py
apertium_lint/tests/test_dix.py
apertium_lint/tests/test_lexc.py
apertium_lint/tests/test_lexd.py
apertium_lint/tests/test_modes.py
apertium_lint/tests/test_rtx.py
apertium_lint/tests/test_transfer.py
apertium_lint/tests/test_twolc.py
apertium_lint/tree_sitter/__init__.py
apertium_lint/tree_sitter/cg.py
apertium_lint/tree_sitter/lexc.py
apertium_lint/tree_sitter/lexd.py
apertium_lint/tree_sitter/rtx.py
apertium_lint/tree_sitter/tree_sitter_linter.py
apertium_lint/tree_sitter/twolc.py
apertium_lint/xml/__init__.py
apertium_lint/xml/dix.py
apertium_lint/xml/lrx.py
apertium_lint/xml/modes.py
apertium_lint/xml/transfer.py
apertium_lint/xml/xml.py
apertium_lint-1.0.11.dist-info/licenses/LICENSE
apertium_lint-1.0.11.dist-info/METADATA
apertium_lint-1.0.11.dist-info/WHEEL
apertium_lint-1.0.11.dist-info/entry_points.txt
apertium_lint-1.0.11.dist-info/top_level.txt
apertium_lint-1.0.11.dist-info/RECORD
