Metadata-Version: 2.4
Name: apertium_lint
Version: 1.0.11
Summary: static analysis of Apertium files
Home-page: http://github.com/apertium/apertium-lint
Author: Daniel Swanson
Author-email: apertium@dangswan.com
License: GPLv3+
Keywords: apertium,linter
License-File: LICENSE
Requires-Dist: tree-sitter<=0.24,>=0.22
Requires-Dist: tree-sitter-apertium>=0.2.0
Requires-Dist: lxml
Dynamic: license-file
